MANIFEST.in
README.rst
setup.cfg
setup.py
livetest/__init__.py
livetest.egg-info/PKG-INFO
livetest.egg-info/SOURCES.txt
livetest.egg-info/dependency_links.txt
livetest.egg-info/not-zip-safe
livetest.egg-info/requires.txt
livetest.egg-info/top_level.txt
test/__init__.py
test/fixtures.py
test/test_fragments.py
test/test_https.py
test/test_input.py
test/test_select.py
test/test_testing.py