Metadata-Version: 1.0
Name: livetest
Version: 0.4
Summary: Make live website tests look like Paste WebTest
Home-page: http://github.com/storborg/livetest
Author: Scott Torborg
Author-email: storborg@mit.edu
License: MIT
Keywords: wsgi test unit tests testing web functional
Platform: UNKNOWN
Classifier: Development Status :: 3 - Alpha
Classifier: Environment :: Web Environment
Classifier: Framework :: Paste
Classifier: Intended Audience :: Developers
Classifier: License :: OSI Approved :: MIT License
Classifier: Topic :: Internet :: WWW/HTTP
Classifier: Topic :: Software Development :: Testing
